{
  "gitSyncId": "67d2e714ec16006858a14115_9b094a87-0c7d-4ce9-bcb4-5407d2a64dca",
  "id": "Entries_checkToken.checkToken",
  "pluginId": "js-plugin",
  "pluginType": "JS",
  "unpublishedAction": {
    "actionConfiguration": {
      "encodeParamsToggle": true,
      "jsArguments": [],
      "paginationType": "NONE",
      "timeoutInMillisecond": 10000
    },
    "collectionId": "Entries_checkToken",
    "confirmBeforeExecute": false,
    "datasource": {
      "isAutoGenerated": false,
      "name": "UNUSED_DATASOURCE",
      "pluginId": "js-plugin"
    },
    "dynamicBindingPathList": [
      {
        "key": "body"
      }
    ],
    "executeOnLoad": true,
    "fullyQualifiedName": "checkToken.checkToken",
    "name": "checkToken",
    "pageId": "Entries",
    "userSetOnLoad": true
  }
}