{
  "gitSyncId": "67d2e714ec16006858a14115_6224ae03-8834-48d0-b4e6-f8471d72d51b",
  "id": "Order_helper.getOrderLines",
  "pluginId": "js-plugin",
  "pluginType": "JS",
  "unpublishedAction": {
    "actionConfiguration": {
      "encodeParamsToggle": true,
      "jsArguments": [],
      "paginationType": "NONE",
      "timeoutInMillisecond": 10000
    },
    "collectionId": "Order_helper",
    "confirmBeforeExecute": false,
    "datasource": {
      "isAutoGenerated": false,
      "name": "UNUSED_DATASOURCE",
      "pluginId": "js-plugin"
    },
    "dynamicBindingPathList": [
      {
        "key": "body"
      }
    ],
    "executeOnLoad": false,
    "fullyQualifiedName": "helper.getOrderLines",
    "name": "getOrderLines",
    "pageId": "Order",
    "userSetOnLoad": false
  }
}